prompt_logger/__init__.py
prompt_logger/cli.py
prompt_logger/export.py
prompt_logger/logger.py
prompt_logger/params.py
prompt_logger/version.py
prompt_logger/models/__init__.py
prompt_logger/models/inference.py
tests/__init__.py
tests/prompt_logger/__init__.py
tests/prompt_logger/test_cli.py
tests/prompt_logger/test_logger.py
prompt_logger-0.2.0.dist-info/LICENSE
prompt_logger-0.2.0.dist-info/METADATA
prompt_logger-0.2.0.dist-info/WHEEL
prompt_logger-0.2.0.dist-info/entry_points.txt
prompt_logger-0.2.0.dist-info/top_level.txt
prompt_logger-0.2.0.dist-info/RECORD
