Metadata-Version: 2.1
Name: prompt-logger
Version: 0.2.0
Summary: A tool for logging and exporting AI prompts and responses
Home-page: https://github.com/rotationalio/prompt-logger
Author: Patrick Deziel
Author-email: Patrick Deziel <deziel.patrick@gmail.com>
License: Apache License
Project-URL: Homepage, https://github.com/rotationalio/prompt-logger
Project-URL: Repository, https://github.com/rotationalio/prompt-logger.git
Keywords: ai,logging,prompts,llm,database
Classifier: Development Status :: 4 - Beta
Classifier: Intended Audience :: Developers
Classifier: License :: OSI Approved :: Apache Software License
Classifier: Operating System :: OS Independent
Classifier: Programming Language :: Python :: 3
Classifier: Programming Language :: Python :: 3.8
Classifier: Programming Language :: Python :: 3.9
Classifier: Programming Language :: Python :: 3.10
Classifier: Programming Language :: Python :: 3.11
Requires-Python: >=3.8
License-File: LICENSE
Requires-Dist: sqlalchemy>=2.0.0
